MANIFEST.in
README.md
setup.cfg
setup.py
ARGs_OAP/ARGs_OAP.py
ARGs_OAP/README.md
ARGs_OAP/__init__.py
ARGs_OAP/argoap_pipeline_stageone_version2
ARGs_OAP/argoap_pipeline_stageone_version2.3
ARGs_OAP/argoap_pipeline_stagetwo_version2
ARGs_OAP/index.rst
ARGs_OAP/stage_one.py
ARGs_OAP/stage_two.py
ARGs_OAP.egg-info/PKG-INFO
ARGs_OAP.egg-info/SOURCES.txt
ARGs_OAP.egg-info/dependency_links.txt
ARGs_OAP.egg-info/entry_points.txt
ARGs_OAP.egg-info/top_level.txt
ARGs_OAP/DB/KO30_DIAMOND.dmnd
ARGs_OAP/DB/SARG.2.2.diamondv0.9.24.dmnd
ARGs_OAP/DB/SARG.2.2.fasta
ARGs_OAP/DB/SARG.2.2.fasta.phr
ARGs_OAP/DB/SARG.2.2.fasta.pin
ARGs_OAP/DB/SARG.2.2.fasta.psq
ARGs_OAP/DB/all_KO30_name.list
ARGs_OAP/DB/gg85.fasta
ARGs_OAP/DB/gg85_yinxiaole.fasta.mmi
ARGs_OAP/DB/structure_20181107.LIST
ARGs_OAP/DB/update_45_sarg2.0_16s.table_201704.txt
ARGs_OAP/DB/update_45_sarg2.0_cell.table_201704.txt
ARGs_OAP/bin/Fq2fa.pl
ARGs_OAP/bin/blastx
ARGs_OAP/bin/copy_correction.pl
ARGs_OAP/bin/de-replicate.pl
ARGs_OAP/bin/diamond
ARGs_OAP/bin/diamondv0.9.24
ARGs_OAP/bin/divide_extract.fa_meta_data_online.pl
ARGs_OAP/bin/extract_usearch_reads.pl
ARGs_OAP/bin/fastp
ARGs_OAP/bin/merge_extracted_fa_update_metadate.v2.3.pl
ARGs_OAP/bin/minimap2
ARGs_OAP/bin/obtain_community.pl
ARGs_OAP/bin/samtools
ARGs_OAP/bin/bbmap/README.md
ARGs_OAP/bin/bbmap/a_sample_mt.sh
ARGs_OAP/bin/bbmap/addadapters.sh
ARGs_OAP/bin/bbmap/addssu.sh
ARGs_OAP/bin/bbmap/adjusthomopolymers.sh
ARGs_OAP/bin/bbmap/alltoall.sh
ARGs_OAP/bin/bbmap/analyzeaccession.sh
ARGs_OAP/bin/bbmap/analyzegenes.sh
ARGs_OAP/bin/bbmap/analyzesketchresults.sh
ARGs_OAP/bin/bbmap/applyvariants.sh
ARGs_OAP/bin/bbmap/bbcms.sh
ARGs_OAP/bin/bbmap/bbcountunique.sh
ARGs_OAP/bin/bbmap/bbduk.sh
ARGs_OAP/bin/bbmap/bbest.sh
ARGs_OAP/bin/bbmap/bbfakereads.sh
ARGs_OAP/bin/bbmap/bbmap.sh
ARGs_OAP/bin/bbmap/bbmapskimmer.sh
ARGs_OAP/bin/bbmap/bbmask.sh
ARGs_OAP/bin/bbmap/bbmerge-auto.sh
ARGs_OAP/bin/bbmap/bbmerge.sh
ARGs_OAP/bin/bbmap/bbnorm.sh
ARGs_OAP/bin/bbmap/bbrealign.sh
ARGs_OAP/bin/bbmap/bbrename.sh
ARGs_OAP/bin/bbmap/bbsketch.sh
ARGs_OAP/bin/bbmap/bbsplit.sh
ARGs_OAP/bin/bbmap/bbsplitpairs.sh
ARGs_OAP/bin/bbmap/bbstats.sh
