Metadata-Version: 2.1
Name: ARGs-OAP
Version: 2.3.2
Summary: test version
Home-page: UNKNOWN
Author: 
Author-email: 
License: MIT
Platform: UNKNOWN
Classifier: Intended Audience :: Developers
Classifier: Programming Language :: Python :: 3
